{"metadata": {"dbt_schema_version": "https://schemas.getdbt.com/dbt/run-results/v4.json", "dbt_version": "1.6.9", "generated_at": "2023-12-27T16:38:14.282490Z", "invocation_id": "ad9b7031-b6a8-4b8a-94f6-082af4209b35", "env": {}}, "results": [{"status": "success", "timing": [{"name": "compile", "started_at": "2023-12-27T16:38:08.103561Z", "completed_at": "2023-12-27T16:38:08.547117Z"}, {"name": "execute", "started_at": "2023-12-27T16:38:08.548131Z", "completed_at": "2023-12-27T16:38:08.548135Z"}], "thread_id": "Thread-4 (worker)", "execution_time": 0.5265350341796875, "adapter_response": {}, "message": null, "failures": null, "unique_id": "model.zendesk_source.stg_zendesk__domain_name_tmp"}, {"status": "success", "timing": [{"name": "compile", "started_at": "2023-12-27T16:38:08.098272Z", "completed_at": "2023-12-27T16:38:08.546789Z"}, {"name": "execute", "started_at": "2023-12-27T16:38:08.547852Z", "completed_at": "2023-12-27T16:38:08.547871Z"}], "thread_id": "Thread-3 (worker)", "execution_time": 0.5343902111053467, "adapter_response": {}, "message": null, "failures": null, "unique_id": "model.zendesk_source.stg_zendesk__daylight_time_tmp"}, {"status": "success", "timing": [{"name": "compile", "started_at": "2023-12-27T16:38:08.076785Z", "completed_at": "2023-12-27T16:38:08.569412Z"}, {"name": "execute", "started_at": "2023-12-27T16:38:08.569934Z", "completed_at": "2023-12-27T16:38:08.569941Z"}], "thread_id": "Thread-2 (worker)", "execution_time": 0.5511560440063477, "adapter_response": {}, "message": null, "failures": null, "unique_id": "model.zendesk_source.stg_zendesk__brand_tmp"}, {"status": "success", "timing": [{"name": "compile", "started_at": "2023-12-27T16:38:08.589587Z", "completed_at": "2023-12-27T16:38:09.012591Z"}, {"name": "execute", "started_at": "2023-12-27T16:38:09.013263Z", "completed_at": "2023-12-27T16:38:09.013270Z"}], "thread_id": "Thread-4 (worker)", "execution_time": 0.47330689430236816, "adapter_response": {}, "message": null, "failures": null, "unique_id": "model.zendesk_source.stg_zendesk__group_tmp"}, {"status": "success", "timing": [{"name": "compile", "started_at": "2023-12-27T16:38:08.612941Z", "completed_at": "2023-12-27T16:38:09.056398Z"}, {"name": "execute", "started_at": "2023-12-27T16:38:09.057437Z", "completed_at": "2023-12-27T16:38:09.057440Z"}], "thread_id": "Thread-2 (worker)", "execution_time": 0.48851776123046875, "adapter_response": {}, "message": null, "failures": null, "unique_id": "model.zendesk_source.stg_zendesk__organization_tmp"}, {"status": "success", "timing": [{"name": "compile", "started_at": "2023-12-27T16:38:08.602686Z", "completed_at": "2023-12-27T16:38:09.056060Z"}, {"name": "execute", "started_at": "2023-12-27T16:38:09.057171Z", "completed_at": "2023-12-27T16:38:09.057178Z"}], "thread_id": "Thread-3 (worker)", "execution_time": 0.49945688247680664, "adapter_response": {}, "message": null, "failures": null, "unique_id": "model.zendesk_source.stg_zendesk__organization_tag_tmp"}, {"status": "success", "timing": [{"name": "compile", "started_at": "2023-12-27T16:38:08.652404Z", "completed_at": "2023-12-27T16:38:09.070881Z"}, {"name": "execute", "started_at": "2023-12-27T16:38:09.071404Z", "completed_at": "2023-12-27T16:38:09.071410Z"}], "thread_id": "Thread-1 (worker)", "execution_time": 0.5008499622344971, "adapter_response": {}, "message": null, "failures": null, "unique_id": "model.zendesk_source.stg_zendesk__schedule_holiday_tmp"}, {"status": "success", "timing": [{"name": "compile", "started_at": "2023-12-27T16:38:09.063568Z", "completed_at": "2023-12-27T16:38:09.507165Z"}, {"name": "execute", "started_at": "2023-12-27T16:38:09.507755Z", "completed_at": "2023-12-27T16:38:09.507763Z"}], "thread_id": "Thread-4 (worker)", "execution_time": 0.484328031539917, "adapter_response": {}, "message": null, "failures": null, "unique_id": "model.zendesk_source.stg_zendesk__schedule_tmp"}, {"status": "success", "timing": [{"name": "compile", "started_at": "2023-12-27T16:38:09.154911Z", "completed_at": "2023-12-27T16:38:09.617913Z"}, {"name": "execute", "started_at": "2023-12-27T16:38:09.618540Z", "completed_at": "2023-12-27T16:38:09.618547Z"}], "thread_id": "Thread-1 (worker)", "execution_time": 0.5109071731567383, "adapter_response": {}, "message": null, "failures": null, "unique_id": "model.zendesk_source.stg_zendesk__ticket_form_history_tmp"}, {"status": "success", "timing": [{"name": "compile", "started_at": "2023-12-27T16:38:09.108062Z", "completed_at": "2023-12-27T16:38:09.623049Z"}, {"name": "execute", "started_at": "2023-12-27T16:38:09.624133Z", "completed_at": "2023-12-27T16:38:09.624136Z"}], "thread_id": "Thread-3 (worker)", "execution_time": 0.5718119144439697, "adapter_response": {}, "message": null, "failures": null, "unique_id": "model.zendesk_source.stg_zendesk__ticket_field_history_tmp"}, {"status": "success", "timing": [{"name": "compile", "started_at": "2023-12-27T16:38:09.103652Z", "completed_at": "2023-12-27T16:38:09.622773Z"}, {"name": "execute", "started_at": "2023-12-27T16:38:09.623868Z", "completed_at": "2023-12-27T16:38:09.623873Z"}], "thread_id": "Thread-2 (worker)", "execution_time": 0.5729351043701172, "adapter_response": {}, "message": null, "failures": null, "unique_id": "model.zendesk_source.stg_zendesk__ticket_comment_tmp"}, {"status": "success", "timing": [{"name": "compile", "started_at": "2023-12-27T16:38:09.548742Z", "completed_at": "2023-12-27T16:38:09.973606Z"}, {"name": "execute", "started_at": "2023-12-27T16:38:09.974377Z", "completed_at": "2023-12-27T16:38:09.974385Z"}], "thread_id": "Thread-4 (worker)", "execution_time": 0.4672071933746338, "adapter_response": {}, "message": null, "failures": null, "unique_id": "model.zendesk_source.stg_zendesk__ticket_schedule_tmp"}, {"status": "success", "timing": [{"name": "compile", "started_at": "2023-12-27T16:38:09.677711Z", "completed_at": "2023-12-27T16:38:10.092169Z"}, {"name": "execute", "started_at": "2023-12-27T16:38:10.092704Z", "completed_at": "2023-12-27T16:38:10.092711Z"}], "thread_id": "Thread-3 (worker)", "execution_time": 0.4594569206237793, "adapter_response": {}, "message": null, "failures": null, "unique_id": "model.zendesk_source.stg_zendesk__ticket_tmp"}, {"status": "success", "timing": [{"name": "compile", "started_at": "2023-12-27T16:38:09.669412Z", "completed_at": "2023-12-27T16:38:10.094928Z"}, {"name": "execute", "started_at": "2023-12-27T16:38:10.095412Z", "completed_at": "2023-12-27T16:38:10.095416Z"}], "thread_id": "Thread-1 (worker)", "execution_time": 0.47019290924072266, "adapter_response": {}, "message": null, "failures": null, "unique_id": "model.zendesk_source.stg_zendesk__ticket_tag_tmp"}, {"status": "success", "timing": [{"name": "compile", "started_at": "2023-12-27T16:38:10.145566Z", "completed_at": "2023-12-27T16:38:10.149273Z"}, {"name": "execute", "started_at": "2023-12-27T16:38:10.151112Z", "completed_at": "2023-12-27T16:38:10.151119Z"}], "thread_id": "Thread-1 (worker)", "execution_time": 0.011976957321166992, "adapter_response": {}, "message": null, "failures": null, "unique_id": "operation.zendesk.zendesk-on-run-start-0"}, {"status": "success", "timing": [{"name": "compile", "started_at": "2023-12-27T16:38:10.153409Z", "completed_at": "2023-12-27T16:38:10.154655Z"}, {"name": "execute", "started_at": "2023-12-27T16:38:10.155683Z", "completed_at": "2023-12-27T16:38:10.155687Z"}], "thread_id": "Thread-1 (worker)", "execution_time": 0.003847837448120117, "adapter_response": {}, "message": null, "failures": null, "unique_id": "seed.zendesk_integration_tests.brand_data_postgres"}, {"status": "success", "timing": [{"name": "compile", "started_at": "2023-12-27T16:38:10.157385Z", "completed_at": "2023-12-27T16:38:10.158457Z"}, {"name": "execute", "started_at": "2023-12-27T16:38:10.158957Z", "completed_at": "2023-12-27T16:38:10.158960Z"}], "thread_id": "Thread-1 (worker)", "execution_time": 0.002635955810546875, "adapter_response": {}, "message": null, "failures": null, "unique_id": "seed.zendesk_integration_tests.daylight_time_data"}, {"status": "success", "timing": [{"name": "compile", "started_at": "2023-12-27T16:38:10.160828Z", "completed_at": "2023-12-27T16:38:10.163067Z"}, {"name": "execute", "started_at": "2023-12-27T16:38:10.163890Z", "completed_at": "2023-12-27T16:38:10.163897Z"}], "thread_id": "Thread-1 (worker)", "execution_time": 0.004519939422607422, "adapter_response": {}, "message": null, "failures": null, "unique_id": "seed.zendesk_integration_tests.domain_name_data"}, {"status": "success", "timing": [{"name": "compile", "started_at": "2023-12-27T16:38:10.166042Z", "completed_at": "2023-12-27T16:38:10.167306Z"}, {"name": "execute", "started_at": "2023-12-27T16:38:10.167857Z", "completed_at": "2023-12-27T16:38:10.167867Z"}], "thread_id": "Thread-1 (worker)", "execution_time": 0.0030012130737304688, "adapter_response": {}, "message": null, "failures": null, "unique_id": "seed.zendesk_integration_tests.group_data"}, {"status": "success", "timing": [{"name": "compile", "started_at": "2023-12-27T16:38:10.169575Z", "completed_at": "2023-12-27T16:38:10.170787Z"}, {"name": "execute", "started_at": "2023-12-27T16:38:10.171333Z", "completed_at": "2023-12-27T16:38:10.171337Z"}], "thread_id": "Thread-1 (worker)", "execution_time": 0.0028748512268066406, "adapter_response": {}, "message": null, "failures": null, "unique_id": "seed.zendesk_integration_tests.organization_data"}, {"status": "success", "timing": [{"name": "compile", "started_at": "2023-12-27T16:38:10.172967Z", "completed_at": "2023-12-27T16:38:10.174075Z"}, {"name": "execute", "started_at": "2023-12-27T16:38:10.174583Z", "completed_at": "2023-12-27T16:38:10.174586Z"}], "thread_id": "Thread-1 (worker)", "execution_time": 0.0026068687438964844, "adapter_response": {}, "message": null, "failures": null, "unique_id": "seed.zendesk_integration_tests.organization_tag_data"}, {"status": "success", "timing": [{"name": "compile", "started_at": "2023-12-27T16:38:10.176201Z", "completed_at": "2023-12-27T16:38:10.177341Z"}, {"name": "execute", "started_at": "2023-12-27T16:38:10.177848Z", "completed_at": "2023-12-27T16:38:10.177852Z"}], "thread_id": "Thread-1 (worker)", "execution_time": 0.0027191638946533203, "adapter_response": {}, "message": null, "failures": null, "unique_id": "seed.zendesk_integration_tests.schedule_data"}, {"status": "success", "timing": [{"name": "compile", "started_at": "2023-12-27T16:38:10.179594Z", "completed_at": "2023-12-27T16:38:10.181364Z"}, {"name": "execute", "started_at": "2023-12-27T16:38:10.181907Z", "completed_at": "2023-12-27T16:38:10.181914Z"}], "thread_id": "Thread-1 (worker)", "execution_time": 0.0034809112548828125, "adapter_response": {}, "message": null, "failures": null, "unique_id": "seed.zendesk_integration_tests.schedule_holiday_data"}, {"status": "success", "timing": [{"name": "compile", "started_at": "2023-12-27T16:38:10.183605Z", "completed_at": "2023-12-27T16:38:10.184786Z"}, {"name": "execute", "started_at": "2023-12-27T16:38:10.185283Z", "completed_at": "2023-12-27T16:38:10.185287Z"}], "thread_id": "Thread-1 (worker)", "execution_time": 0.0027239322662353516, "adapter_response": {}, "message": null, "failures": null, "unique_id": "seed.zendesk_integration_tests.ticket_comment_data"}, {"status": "success", "timing": [{"name": "compile", "started_at": "2023-12-27T16:38:10.186847Z", "completed_at": "2023-12-27T16:38:10.187955Z"}, {"name": "execute", "started_at": "2023-12-27T16:38:10.188439Z", "completed_at": "2023-12-27T16:38:10.188444Z"}], "thread_id": "Thread-1 (worker)", "execution_time": 0.002609729766845703, "adapter_response": {}, "message": null, "failures": null, "unique_id": "seed.zendesk_integration_tests.ticket_data"}, {"status": "success", "timing": [{"name": "compile", "started_at": "2023-12-27T16:38:10.190009Z", "completed_at": "2023-12-27T16:38:10.191134Z"}, {"name": "execute", "started_at": "2023-12-27T16:38:10.191644Z", "completed_at": "2023-12-27T16:38:10.191648Z"}], "thread_id": "Thread-1 (worker)", "execution_time": 0.0026388168334960938, "adapter_response": {}, "message": null, "failures": null, "unique_id": "seed.zendesk_integration_tests.ticket_field_history_data"}, {"status": "success", "timing": [{"name": "compile", "started_at": "2023-12-27T16:38:10.193267Z", "completed_at": "2023-12-27T16:38:10.194389Z"}, {"name": "execute", "started_at": "2023-12-27T16:38:10.194908Z", "completed_at": "2023-12-27T16:38:10.194912Z"}], "thread_id": "Thread-1 (worker)", "execution_time": 0.0027000904083251953, "adapter_response": {}, "message": null, "failures": null, "unique_id": "seed.zendesk_integration_tests.ticket_form_history_data"}, {"status": "success", "timing": [{"name": "compile", "started_at": "2023-12-27T16:38:09.681789Z", "completed_at": "2023-12-27T16:38:10.152646Z"}, {"name": "execute", "started_at": "2023-12-27T16:38:10.154962Z", "completed_at": "2023-12-27T16:38:10.154967Z"}], "thread_id": "Thread-2 (worker)", "execution_time": 0.52276611328125, "adapter_response": {}, "message": null, "failures": null, "unique_id": "model.zendesk_source.stg_zendesk__time_zone_tmp"}, {"status": "success", "timing": [{"name": "compile", "started_at": "2023-12-27T16:38:10.196561Z", "completed_at": "2023-12-27T16:38:10.197696Z"}, {"name": "execute", "started_at": "2023-12-27T16:38:10.198456Z", "completed_at": "2023-12-27T16:38:10.198460Z"}], "thread_id": "Thread-1 (worker)", "execution_time": 0.004225969314575195, "adapter_response": {}, "message": null, "failures": null, "unique_id": "seed.zendesk_integration_tests.ticket_schedule_data"}, {"status": "success", "timing": [{"name": "compile", "started_at": "2023-12-27T16:38:10.202275Z", "completed_at": "2023-12-27T16:38:10.203435Z"}, {"name": "execute", "started_at": "2023-12-27T16:38:10.205456Z", "completed_at": "2023-12-27T16:38:10.205462Z"}], "thread_id": "Thread-2 (worker)", "execution_time": 0.005023002624511719, "adapter_response": {}, "message": null, "failures": null, "unique_id": "seed.zendesk_integration_tests.ticket_tag_data"}, {"status": "success", "timing": [{"name": "compile", "started_at": "2023-12-27T16:38:10.203716Z", "completed_at": "2023-12-27T16:38:10.204756Z"}, {"name": "execute", "started_at": "2023-12-27T16:38:10.205711Z", "completed_at": "2023-12-27T16:38:10.205713Z"}], "thread_id": "Thread-1 (worker)", "execution_time": 0.005145072937011719, "adapter_response": {}, "message": null, "failures": null, "unique_id": "seed.zendesk_integration_tests.time_zone_data"}, {"status": "success", "timing": [{"name": "compile", "started_at": "2023-12-27T16:38:10.208668Z", "completed_at": "2023-12-27T16:38:10.209848Z"}, {"name": "execute", "started_at": "2023-12-27T16:38:10.211905Z", "completed_at": "2023-12-27T16:38:10.211909Z"}], "thread_id": "Thread-2 (worker)", "execution_time": 0.005084037780761719, "adapter_response": {}, "message": null, "failures": null, "unique_id": "seed.zendesk_integration_tests.user_data"}, {"status": "success", "timing": [{"name": "compile", "started_at": "2023-12-27T16:38:10.210141Z", "completed_at": "2023-12-27T16:38:10.211173Z"}, {"name": "execute", "started_at": "2023-12-27T16:38:10.212159Z", "completed_at": "2023-12-27T16:38:10.212162Z"}], "thread_id": "Thread-1 (worker)", "execution_time": 0.005170106887817383, "adapter_response": {}, "message": null, "failures": null, "unique_id": "seed.zendesk_integration_tests.user_tag_data"}, {"status": "success", "timing": [{"name": "compile", "started_at": "2023-12-27T16:38:10.021048Z", "completed_at": "2023-12-27T16:38:10.455484Z"}, {"name": "execute", "started_at": "2023-12-27T16:38:10.456049Z", "completed_at": "2023-12-27T16:38:10.456057Z"}], "thread_id": "Thread-4 (worker)", "execution_time": 0.4843277931213379, "adapter_response": {}, "message": null, "failures": null, "unique_id": "model.zendesk_source.stg_zendesk__user_tag_tmp"}, {"status": "success", "timing": [{"name": "compile", "started_at": "2023-12-27T16:38:10.140475Z", "completed_at": "2023-12-27T16:38:10.565512Z"}, {"name": "execute", "started_at": "2023-12-27T16:38:10.566030Z", "completed_at": "2023-12-27T16:38:10.566037Z"}], "thread_id": "Thread-3 (worker)", "execution_time": 0.47524309158325195, "adapter_response": {}, "message": null, "failures": null, "unique_id": "model.zendesk_source.stg_zendesk__user_tmp"}, {"status": "success", "timing": [{"name": "compile", "started_at": "2023-12-27T16:38:10.215063Z", "completed_at": "2023-12-27T16:38:10.647411Z"}, {"name": "execute", "started_at": "2023-12-27T16:38:10.648002Z", "completed_at": "2023-12-27T16:38:10.648013Z"}], "thread_id": "Thread-2 (worker)", "execution_time": 0.474473237991333, "adapter_response": {}, "message": null, "failures": null, "unique_id": "model.zendesk_source.stg_zendesk__domain_name"}, {"status": "success", "timing": [{"name": "compile", "started_at": "2023-12-27T16:38:10.220245Z", "completed_at": "2023-12-27T16:38:10.694243Z"}, {"name": "execute", "started_at": "2023-12-27T16:38:10.695351Z", "completed_at": "2023-12-27T16:38:10.695357Z"}], "thread_id": "Thread-1 (worker)", "execution_time": 0.5287199020385742, "adapter_response": {}, "message": null, "failures": null, "unique_id": "model.zendesk_source.stg_zendesk__daylight_time"}, {"status": "success", "timing": [{"name": "compile", "started_at": "2023-12-27T16:38:10.503924Z", "completed_at": "2023-12-27T16:38:10.955768Z"}, {"name": "execute", "started_at": "2023-12-27T16:38:10.956306Z", "completed_at": "2023-12-27T16:38:10.956313Z"}], "thread_id": "Thread-4 (worker)", "execution_time": 0.4947068691253662, "adapter_response": {}, "message": null, "failures": null, "unique_id": "model.zendesk_source.stg_zendesk__brand"}, {"status": "success", "timing": [{"name": "compile", "started_at": "2023-12-27T16:38:10.615943Z", "completed_at": "2023-12-27T16:38:11.024214Z"}, {"name": "execute", "started_at": "2023-12-27T16:38:11.024748Z", "completed_at": "2023-12-27T16:38:11.024755Z"}], "thread_id": "Thread-3 (worker)", "execution_time": 0.4475977420806885, "adapter_response": {}, "message": null, "failures": null, "unique_id": "model.zendesk_source.stg_zendesk__group"}, {"status": "success", "timing": [{"name": "compile", "started_at": "2023-12-27T16:38:10.689921Z", "completed_at": "2023-12-27T16:38:11.151231Z"}, {"name": "execute", "started_at": "2023-12-27T16:38:11.151778Z", "completed_at": "2023-12-27T16:38:11.151785Z"}], "thread_id": "Thread-2 (worker)", "execution_time": 0.5092339515686035, "adapter_response": {}, "message": null, "failures": null, "unique_id": "model.zendesk_source.stg_zendesk__organization"}, {"status": "success", "timing": [{"name": "compile", "started_at": "2023-12-27T16:38:10.745130Z", "completed_at": "2023-12-27T16:38:11.268868Z"}, {"name": "execute", "started_at": "2023-12-27T16:38:11.269408Z", "completed_at": "2023-12-27T16:38:11.269415Z"}], "thread_id": "Thread-1 (worker)", "execution_time": 0.5841429233551025, "adapter_response": {}, "message": null, "failures": null, "unique_id": "model.zendesk_source.stg_zendesk__organization_tag"}, {"status": "success", "timing": [{"name": "compile", "started_at": "2023-12-27T16:38:11.000234Z", "completed_at": "2023-12-27T16:38:11.471197Z"}, {"name": "execute", "started_at": "2023-12-27T16:38:11.471725Z", "completed_at": "2023-12-27T16:38:11.471731Z"}], "thread_id": "Thread-4 (worker)", "execution_time": 0.5168578624725342, "adapter_response": {}, "message": null, "failures": null, "unique_id": "model.zendesk_source.stg_zendesk__schedule_holiday"}, {"status": "success", "timing": [{"name": "compile", "started_at": "2023-12-27T16:38:11.064318Z", "completed_at": "2023-12-27T16:38:11.572779Z"}, {"name": "execute", "started_at": "2023-12-27T16:38:11.573335Z", "completed_at": "2023-12-27T16:38:11.573342Z"}], "thread_id": "Thread-3 (worker)", "execution_time": 0.5502529144287109, "adapter_response": {}, "message": null, "failures": null, "unique_id": "model.zendesk_source.stg_zendesk__schedule"}, {"status": "success", "timing": [{"name": "compile", "started_at": "2023-12-27T16:38:11.200953Z", "completed_at": "2023-12-27T16:38:11.672089Z"}, {"name": "execute", "started_at": "2023-12-27T16:38:11.672628Z", "completed_at": "2023-12-27T16:38:11.672635Z"}], "thread_id": "Thread-2 (worker)", "execution_time": 0.5123858451843262, "adapter_response": {}, "message": null, "failures": null, "unique_id": "model.zendesk_source.stg_zendesk__ticket_form_history"}, {"status": "success", "timing": [{"name": "compile", "started_at": "2023-12-27T16:38:11.329478Z", "completed_at": "2023-12-27T16:38:11.826935Z"}, {"name": "execute", "started_at": "2023-12-27T16:38:11.827503Z", "completed_at": "2023-12-27T16:38:11.827510Z"}], "thread_id": "Thread-1 (worker)", "execution_time": 0.5420832633972168, "adapter_response": {}, "message": null, "failures": null, "unique_id": "model.zendesk_source.stg_zendesk__ticket_field_history"}, {"status": "success", "timing": [{"name": "compile", "started_at": "2023-12-27T16:38:11.517781Z", "completed_at": "2023-12-27T16:38:11.960354Z"}, {"name": "execute", "started_at": "2023-12-27T16:38:11.960921Z", "completed_at": "2023-12-27T16:38:11.960928Z"}], "thread_id": "Thread-4 (worker)", "execution_time": 0.4818422794342041, "adapter_response": {}, "message": null, "failures": null, "unique_id": "model.zendesk_source.stg_zendesk__ticket_comment"}, {"status": "success", "timing": [{"name": "compile", "started_at": "2023-12-27T16:38:11.615217Z", "completed_at": "2023-12-27T16:38:12.037027Z"}, {"name": "execute", "started_at": "2023-12-27T16:38:12.037565Z", "completed_at": "2023-12-27T16:38:12.037572Z"}], "thread_id": "Thread-3 (worker)", "execution_time": 0.4635190963745117, "adapter_response": {}, "message": null, "failures": null, "unique_id": "model.zendesk_source.stg_zendesk__ticket_schedule"}, {"status": "success", "timing": [{"name": "compile", "started_at": "2023-12-27T16:38:11.714323Z", "completed_at": "2023-12-27T16:38:12.192418Z"}, {"name": "execute", "started_at": "2023-12-27T16:38:12.192974Z", "completed_at": "2023-12-27T16:38:12.192982Z"}], "thread_id": "Thread-2 (worker)", "execution_time": 0.5217657089233398, "adapter_response": {}, "message": null, "failures": null, "unique_id": "model.zendesk_source.stg_zendesk__ticket"}, {"status": "success", "timing": [{"name": "compile", "started_at": "2023-12-27T16:38:11.873034Z", "completed_at": "2023-12-27T16:38:12.341196Z"}, {"name": "execute", "started_at": "2023-12-27T16:38:12.341741Z", "completed_at": "2023-12-27T16:38:12.341748Z"}], "thread_id": "Thread-1 (worker)", "execution_time": 0.5250780582427979, "adapter_response": {}, "message": null, "failures": null, "unique_id": "model.zendesk_source.stg_zendesk__ticket_tag"}, {"status": "success", "timing": [{"name": "compile", "started_at": "2023-12-27T16:38:12.400952Z", "completed_at": "2023-12-27T16:38:12.409712Z"}, {"name": "execute", "started_at": "2023-12-27T16:38:12.410259Z", "completed_at": "2023-12-27T16:38:12.410265Z"}], "thread_id": "Thread-1 (worker)", "execution_time": 0.010557174682617188, "adapter_response": {}, "message": null, "failures": null, "unique_id": "test.zendesk_source.not_null_stg_zendesk__domain_name_organization_id.a2b5ff8fd3"}, {"status": "success", "timing": [{"name": "compile", "started_at": "2023-12-27T16:38:12.412068Z", "completed_at": "2023-12-27T16:38:12.418756Z"}, {"name": "execute", "started_at": "2023-12-27T16:38:12.419289Z", "completed_at": "2023-12-27T16:38:12.419295Z"}], "thread_id": "Thread-1 (worker)", "execution_time": 0.008363008499145508, "adapter_response": {}, "message": null, "failures": null, "unique_id": "test.zendesk_source.dbt_utils_unique_combination_of_columns_stg_zendesk__daylight_time_time_zone__year.88227aef3d"}, {"status": "success", "timing": [{"name": "compile", "started_at": "2023-12-27T16:38:12.421011Z", "completed_at": "2023-12-27T16:38:12.424061Z"}, {"name": "execute", "started_at": "2023-12-27T16:38:12.424554Z", "completed_at": "2023-12-27T16:38:12.424559Z"}], "thread_id": "Thread-1 (worker)", "execution_time": 0.00461888313293457, "adapter_response": {}, "message": null, "failures": null, "unique_id": "test.zendesk_source.not_null_stg_zendesk__brand_brand_id.a2419e1741"}, {"status": "success", "timing": [{"name": "compile", "started_at": "2023-12-27T16:38:12.426145Z", "completed_at": "2023-12-27T16:38:12.431289Z"}, {"name": "execute", "started_at": "2023-12-27T16:38:12.431786Z", "completed_at": "2023-12-27T16:38:12.431792Z"}], "thread_id": "Thread-1 (worker)", "execution_time": 0.006638765335083008, "adapter_response": {}, "message": null, "failures": null, "unique_id": "test.zendesk_source.unique_stg_zendesk__brand_brand_id.fdf8e23c9e"}, {"status": "success", "timing": [{"name": "compile", "started_at": "2023-12-27T16:38:12.433360Z", "completed_at": "2023-12-27T16:38:12.436497Z"}, {"name": "execute", "started_at": "2023-12-27T16:38:12.437019Z", "completed_at": "2023-12-27T16:38:12.437024Z"}], "thread_id": "Thread-1 (worker)", "execution_time": 0.004648923873901367, "adapter_response": {}, "message": null, "failures": null, "unique_id": "test.zendesk_source.not_null_stg_zendesk__group_group_id.7659ed83ec"}, {"status": "success", "timing": [{"name": "compile", "started_at": "2023-12-27T16:38:12.438601Z", "completed_at": "2023-12-27T16:38:12.442070Z"}, {"name": "execute", "started_at": "2023-12-27T16:38:12.442640Z", "completed_at": "2023-12-27T16:38:12.442645Z"}], "thread_id": "Thread-1 (worker)", "execution_time": 0.005056619644165039, "adapter_response": {}, "message": null, "failures": null, "unique_id": "test.zendesk_source.unique_stg_zendesk__group_group_id.f0658dabcd"}, {"status": "success", "timing": [{"name": "compile", "started_at": "2023-12-27T16:38:12.444337Z", "completed_at": "2023-12-27T16:38:12.447312Z"}, {"name": "execute", "started_at": "2023-12-27T16:38:12.447803Z", "completed_at": "2023-12-27T16:38:12.447808Z"}], "thread_id": "Thread-1 (worker)", "execution_time": 0.004509925842285156, "adapter_response": {}, "message": null, "failures": null, "unique_id": "test.zendesk_source.not_null_stg_zendesk__organization_organization_id.de7b98c06a"}, {"status": "success", "timing": [{"name": "compile", "started_at": "2023-12-27T16:38:12.449524Z", "completed_at": "2023-12-27T16:38:12.453352Z"}, {"name": "execute", "started_at": "2023-12-27T16:38:12.453865Z", "completed_at": "2023-12-27T16:38:12.453870Z"}], "thread_id": "Thread-1 (worker)", "execution_time": 0.005450010299682617, "adapter_response": {}, "message": null, "failures": null, "unique_id": "test.zendesk_source.unique_stg_zendesk__organization_organization_id.152be1ab31"}, {"status": "success", "timing": [{"name": "compile", "started_at": "2023-12-27T16:38:12.455470Z", "completed_at": "2023-12-27T16:38:12.461098Z"}, {"name": "execute", "started_at": "2023-12-27T16:38:12.467707Z", "completed_at": "2023-12-27T16:38:12.467715Z"}], "thread_id": "Thread-1 (worker)", "execution_time": 0.013330936431884766, "adapter_response": {}, "message": null, "failures": null, "unique_id": "model.zendesk.int_zendesk__organization_aggregates"}, {"status": "success", "timing": [{"name": "compile", "started_at": "2023-12-27T16:38:12.470057Z", "completed_at": "2023-12-27T16:38:12.473634Z"}, {"name": "execute", "started_at": "2023-12-27T16:38:12.474111Z", "completed_at": "2023-12-27T16:38:12.474114Z"}], "thread_id": "Thread-1 (worker)", "execution_time": 0.00561213493347168, "adapter_response": {}, "message": null, "failures": null, "unique_id": "test.zendesk_source.not_null_stg_zendesk__schedule_holiday_holiday_id.52eb08f782"}, {"status": "success", "timing": [{"name": "compile", "started_at": "2023-12-27T16:38:12.475716Z", "completed_at": "2023-12-27T16:38:12.478828Z"}, {"name": "execute", "started_at": "2023-12-27T16:38:12.479325Z", "completed_at": "2023-12-27T16:38:12.479330Z"}], "thread_id": "Thread-1 (worker)", "execution_time": 0.004617929458618164, "adapter_response": {}, "message": null, "failures": null, "unique_id": "test.zendesk_source.unique_stg_zendesk__schedule_holiday_holiday_id.0341d5635a"}, {"status": "success", "timing": [{"name": "compile", "started_at": "2023-12-27T16:38:12.480964Z", "completed_at": "2023-12-27T16:38:12.483444Z"}, {"name": "execute", "started_at": "2023-12-27T16:38:12.483931Z", "completed_at": "2023-12-27T16:38:12.483936Z"}], "thread_id": "Thread-1 (worker)", "execution_time": 0.004015922546386719, "adapter_response": {}, "message": null, "failures": null, "unique_id": "model.zendesk.int_zendesk__latest_ticket_form"}, {"status": "success", "timing": [{"name": "compile", "started_at": "2023-12-27T16:38:12.485585Z", "completed_at": "2023-12-27T16:38:12.494213Z"}, {"name": "execute", "started_at": "2023-12-27T16:38:12.494777Z", "completed_at": "2023-12-27T16:38:12.494783Z"}], "thread_id": "Thread-1 (worker)", "execution_time": 0.010277748107910156, "adapter_response": {}, "message": null, "failures": null, "unique_id": "test.zendesk_source.not_null_stg_zendesk__ticket_form_history_ticket_form_id.1afe781a17"}, {"status": "success", "timing": [{"name": "compile", "started_at": "2023-12-27T16:38:12.497546Z", "completed_at": "2023-12-27T16:38:12.500773Z"}, {"name": "execute", "started_at": "2023-12-27T16:38:12.501285Z", "completed_at": "2023-12-27T16:38:12.501289Z"}], "thread_id": "Thread-1 (worker)", "execution_time": 0.0053179264068603516, "adapter_response": {}, "message": null, "failures": null, "unique_id": "test.zendesk_source.not_null_stg_zendesk__ticket_comment_ticket_comment_id.b821f4a606"}, {"status": "success", "timing": [{"name": "compile", "started_at": "2023-12-27T16:38:12.503030Z", "completed_at": "2023-12-27T16:38:12.505902Z"}, {"name": "execute", "started_at": "2023-12-27T16:38:12.506388Z", "completed_at": "2023-12-27T16:38:12.506393Z"}], "thread_id": "Thread-1 (worker)", "execution_time": 0.004374980926513672, "adapter_response": {}, "message": null, "failures": null, "unique_id": "test.zendesk_source.unique_stg_zendesk__ticket_comment_ticket_comment_id.ba353330cd"}, {"status": "success", "timing": [{"name": "compile", "started_at": "2023-12-27T16:38:12.002784Z", "completed_at": "2023-12-27T16:38:12.469321Z"}, {"name": "execute", "started_at": "2023-12-27T16:38:12.472954Z", "completed_at": "2023-12-27T16:38:12.472960Z"}], "thread_id": "Thread-4 (worker)", "execution_time": 0.5243890285491943, "adapter_response": {}, "message": null, "failures": null, "unique_id": "model.zendesk_source.stg_zendesk__time_zone"}, {"status": "success", "timing": [{"name": "compile", "started_at": "2023-12-27T16:38:12.508004Z", "completed_at": "2023-12-27T16:38:12.536858Z"}, {"name": "execute", "started_at": "2023-12-27T16:38:12.537693Z", "completed_at": "2023-12-27T16:38:12.537699Z"}], "thread_id": "Thread-1 (worker)", "execution_time": 0.03073596954345703, "adapter_response": {}, "message": null, "failures": null, "unique_id": "model.zendesk.int_zendesk__field_calendar_spine"}, {"status": "success", "timing": [{"name": "compile", "started_at": "2023-12-27T16:38:12.539391Z", "completed_at": "2023-12-27T16:38:12.542221Z"}, {"name": "execute", "started_at": "2023-12-27T16:38:12.542717Z", "completed_at": "2023-12-27T16:38:12.542722Z"}], "thread_id": "Thread-1 (worker)", "execution_time": 0.004353046417236328, "adapter_response": {}, "message": null, "failures": null, "unique_id": "model.zendesk.int_zendesk__updates"}, {"status": "success", "timing": [{"name": "compile", "started_at": "2023-12-27T16:38:12.079701Z", "completed_at": "2023-12-27T16:38:12.495581Z"}, {"name": "execute", "started_at": "2023-12-27T16:38:12.496777Z", "completed_at": "2023-12-27T16:38:12.496780Z"}], "thread_id": "Thread-3 (worker)", "execution_time": 0.4691030979156494, "adapter_response": {}, "message": null, "failures": null, "unique_id": "model.zendesk_source.stg_zendesk__user_tag"}, {"status": "success", "timing": [{"name": "compile", "started_at": "2023-12-27T16:38:12.544447Z", "completed_at": "2023-12-27T16:38:12.548264Z"}, {"name": "execute", "started_at": "2023-12-27T16:38:12.549432Z", "completed_at": "2023-12-27T16:38:12.549436Z"}], "thread_id": "Thread-1 (worker)", "execution_time": 0.006232023239135742, "adapter_response": {}, "message": null, "failures": null, "unique_id": "test.zendesk_source.not_null_stg_zendesk__ticket_ticket_id.a8229e6981"}, {"status": "success", "timing": [{"name": "compile", "started_at": "2023-12-27T16:38:12.550406Z", "completed_at": "2023-12-27T16:38:12.554160Z"}, {"name": "execute", "started_at": "2023-12-27T16:38:12.558159Z", "completed_at": "2023-12-27T16:38:12.558165Z"}], "thread_id": "Thread-3 (worker)", "execution_time": 0.009550809860229492, "adapter_response": {}, "message": null, "failures": null, "unique_id": "test.zendesk_source.unique_stg_zendesk__ticket_ticket_id.4be7124521"}, {"status": "success", "timing": [{"name": "compile", "started_at": "2023-12-27T16:38:12.554408Z", "completed_at": "2023-12-27T16:38:12.558914Z"}, {"name": "execute", "started_at": "2023-12-27T16:38:12.560034Z", "completed_at": "2023-12-27T16:38:12.560037Z"}], "thread_id": "Thread-1 (worker)", "execution_time": 0.007172107696533203, "adapter_response": {}, "message": null, "failures": null, "unique_id": "model.zendesk.int_zendesk__ticket_aggregates"}, {"status": "success", "timing": [{"name": "compile", "started_at": "2023-12-27T16:38:12.561015Z", "completed_at": "2023-12-27T16:38:12.583709Z"}, {"name": "execute", "started_at": "2023-12-27T16:38:12.584289Z", "completed_at": "2023-12-27T16:38:12.584296Z"}], "thread_id": "Thread-3 (worker)", "execution_time": 0.025079965591430664, "adapter_response": {}, "message": null, "failures": null, "unique_id": "model.zendesk.int_zendesk__schedule_spine"}, {"status": "success", "timing": [{"name": "compile", "started_at": "2023-12-27T16:38:12.580515Z", "completed_at": "2023-12-27T16:38:12.585088Z"}, {"name": "execute", "started_at": "2023-12-27T16:38:12.586288Z", "completed_at": "2023-12-27T16:38:12.586291Z"}], "thread_id": "Thread-1 (worker)", "execution_time": 0.0071239471435546875, "adapter_response": {}, "message": null, "failures": null, "unique_id": "test.zendesk_source.not_null_stg_zendesk__time_zone_time_zone.b25b3452b1"}, {"status": "success", "timing": [{"name": "compile", "started_at": "2023-12-27T16:38:12.587236Z", "completed_at": "2023-12-27T16:38:12.593968Z"}, {"name": "execute", "started_at": "2023-12-27T16:38:12.594565Z", "completed_at": "2023-12-27T16:38:12.594570Z"}], "thread_id": "Thread-3 (worker)", "execution_time": 0.009099960327148438, "adapter_response": {}, "message": null, "failures": null, "unique_id": "test.zendesk_source.unique_stg_zendesk__time_zone_time_zone.67995adbaf"}, {"status": "success", "timing": [{"name": "compile", "started_at": "2023-12-27T16:38:12.590961Z", "completed_at": "2023-12-27T16:38:12.595346Z"}, {"name": "execute", "started_at": "2023-12-27T16:38:12.596488Z", "completed_at": "2023-12-27T16:38:12.596492Z"}], "thread_id": "Thread-1 (worker)", "execution_time": 0.006791114807128906, "adapter_response": {}, "message": null, "failures": null, "unique_id": "model.zendesk.int_zendesk__assignee_updates"}, {"status": "success", "timing": [{"name": "compile", "started_at": "2023-12-27T16:38:12.597465Z", "completed_at": "2023-12-27T16:38:12.603726Z"}, {"name": "execute", "started_at": "2023-12-27T16:38:12.604580Z", "completed_at": "2023-12-27T16:38:12.604586Z"}], "thread_id": "Thread-3 (worker)", "execution_time": 0.009155035018920898, "adapter_response": {}, "message": null, "failures": null, "unique_id": "model.zendesk.int_zendesk__requester_updates"}, {"status": "success", "timing": [{"name": "compile", "started_at": "2023-12-27T16:38:12.600615Z", "completed_at": "2023-12-27T16:38:12.604296Z"}, {"name": "execute", "started_at": "2023-12-27T16:38:12.605609Z", "completed_at": "2023-12-27T16:38:12.605612Z"}], "thread_id": "Thread-1 (worker)", "execution_time": 0.006344795227050781, "adapter_response": {}, "message": null, "failures": null, "unique_id": "model.zendesk.int_zendesk__ticket_historical_assignee"}, {"status": "success", "timing": [{"name": "compile", "started_at": "2023-12-27T16:38:12.607864Z", "completed_at": "2023-12-27T16:38:12.613280Z"}, {"name": "execute", "started_at": "2023-12-27T16:38:12.614093Z", "completed_at": "2023-12-27T16:38:12.614099Z"}], "thread_id": "Thread-3 (worker)", "execution_time": 0.008142709732055664, "adapter_response": {}, "message": null, "failures": null, "unique_id": "model.zendesk.int_zendesk__ticket_historical_group"}, {"status": "success", "timing": [{"name": "compile", "started_at": "2023-12-27T16:38:12.610240Z", "completed_at": "2023-12-27T16:38:12.613801Z"}, {"name": "execute", "started_at": "2023-12-27T16:38:12.615138Z", "completed_at": "2023-12-27T16:38:12.615143Z"}], "thread_id": "Thread-1 (worker)", "execution_time": 0.008366107940673828, "adapter_response": {}, "message": null, "failures": null, "unique_id": "model.zendesk.int_zendesk__ticket_historical_satisfaction"}, {"status": "success", "timing": [{"name": "compile", "started_at": "2023-12-27T16:38:12.617470Z", "completed_at": "2023-12-27T16:38:12.664049Z"}, {"name": "execute", "started_at": "2023-12-27T16:38:12.664869Z", "completed_at": "2023-12-27T16:38:12.664876Z"}], "thread_id": "Thread-3 (worker)", "execution_time": 0.049372196197509766, "adapter_response": {}, "message": null, "failures": null, "unique_id": "model.zendesk.int_zendesk__ticket_historical_status"}, {"status": "success", "timing": [{"name": "compile", "started_at": "2023-12-27T16:38:12.658699Z", "completed_at": "2023-12-27T16:38:12.664574Z"}, {"name": "execute", "started_at": "2023-12-27T16:38:12.665956Z", "completed_at": "2023-12-27T16:38:12.665959Z"}], "thread_id": "Thread-1 (worker)", "execution_time": 0.04966568946838379, "adapter_response": {}, "message": null, "failures": null, "unique_id": "model.zendesk.int_zendesk__sla_policy_applied"}, {"status": "success", "timing": [{"name": "compile", "started_at": "2023-12-27T16:38:12.677419Z", "completed_at": "2023-12-27T16:38:12.683744Z"}, {"name": "execute", "started_at": "2023-12-27T16:38:12.687099Z", "completed_at": "2023-12-27T16:38:12.687105Z"}], "thread_id": "Thread-3 (worker)", "execution_time": 0.011067867279052734, "adapter_response": {}, "message": null, "failures": null, "unique_id": "model.zendesk.int_zendesk__agent_work_time_filtered_statuses"}, {"status": "success", "timing": [{"name": "compile", "started_at": "2023-12-27T16:38:12.684507Z", "completed_at": "2023-12-27T16:38:12.688709Z"}, {"name": "execute", "started_at": "2023-12-27T16:38:12.692381Z", "completed_at": "2023-12-27T16:38:12.692387Z"}], "thread_id": "Thread-1 (worker)", "execution_time": 0.00952005386352539, "adapter_response": {}, "message": null, "failures": null, "unique_id": "model.zendesk.int_zendesk__reply_time_calendar_hours"}, {"status": "success", "timing": [{"name": "compile", "started_at": "2023-12-27T16:38:12.689442Z", "completed_at": "2023-12-27T16:38:12.693926Z"}, {"name": "execute", "started_at": "2023-12-27T16:38:12.698049Z", "completed_at": "2023-12-27T16:38:12.698055Z"}], "thread_id": "Thread-3 (worker)", "execution_time": 0.010262012481689453, "adapter_response": {}, "message": null, "failures": null, "unique_id": "model.zendesk.int_zendesk__requester_wait_time_filtered_statuses"}, {"status": "success", "timing": [{"name": "compile", "started_at": "2023-12-27T16:38:12.694668Z", "completed_at": "2023-12-27T16:38:12.699642Z"}, {"name": "execute", "started_at": "2023-12-27T16:38:12.703650Z", "completed_at": "2023-12-27T16:38:12.703655Z"}], "thread_id": "Thread-1 (worker)", "execution_time": 0.010586977005004883, "adapter_response": {}, "message": null, "failures": null, "unique_id": "model.zendesk.int_zendesk__agent_work_time_calendar_hours"}, {"status": "success", "timing": [{"name": "compile", "started_at": "2023-12-27T16:38:12.700350Z", "completed_at": "2023-12-27T16:38:12.704608Z"}, {"name": "execute", "started_at": "2023-12-27T16:38:12.705087Z", "completed_at": "2023-12-27T16:38:12.705091Z"}], "thread_id": "Thread-3 (worker)", "execution_time": 0.006232023239135742, "adapter_response": {}, "message": null, "failures": null, "unique_id": "model.zendesk.int_zendesk__requester_wait_time_calendar_hours"}, {"status": "success", "timing": [{"name": "compile", "started_at": "2023-12-27T16:38:12.237010Z", "completed_at": "2023-12-27T16:38:12.736103Z"}, {"name": "execute", "started_at": "2023-12-27T16:38:12.736618Z", "completed_at": "2023-12-27T16:38:12.736625Z"}], "thread_id": "Thread-2 (worker)", "execution_time": 0.5433900356292725, "adapter_response": {}, "message": null, "failures": null, "unique_id": "model.zendesk_source.stg_zendesk__user"}, {"status": "success", "timing": [{"name": "compile", "started_at": "2023-12-27T16:38:12.782325Z", "completed_at": "2023-12-27T16:38:12.792002Z"}, {"name": "execute", "started_at": "2023-12-27T16:38:12.792608Z", "completed_at": "2023-12-27T16:38:12.792616Z"}], "thread_id": "Thread-1 (worker)", "execution_time": 0.012593984603881836, "adapter_response": {}, "message": null, "failures": null, "unique_id": "model.zendesk.int_zendesk__user_aggregates"}, {"status": "success", "timing": [{"name": "compile", "started_at": "2023-12-27T16:38:12.789083Z", "completed_at": "2023-12-27T16:38:12.793490Z"}, {"name": "execute", "started_at": "2023-12-27T16:38:12.795218Z", "completed_at": "2023-12-27T16:38:12.795222Z"}], "thread_id": "Thread-2 (worker)", "execution_time": 0.014374971389770508, "adapter_response": {}, "message": null, "failures": null, "unique_id": "test.zendesk_source.unique_stg_zendesk__user_user_id.3d3e346b11"}, {"status": "success", "timing": [{"name": "compile", "started_at": "2023-12-27T16:38:12.786107Z", "completed_at": "2023-12-27T16:38:12.793741Z"}, {"name": "execute", "started_at": "2023-12-27T16:38:12.795480Z", "completed_at": "2023-12-27T16:38:12.795483Z"}], "thread_id": "Thread-3 (worker)", "execution_time": 0.01542210578918457, "adapter_response": {}, "message": null, "failures": null, "unique_id": "test.zendesk_source.not_null_stg_zendesk__user_user_id.102d572926"}, {"status": "success", "timing": [{"name": "compile", "started_at": "2023-12-27T16:38:12.805026Z", "completed_at": "2023-12-27T16:38:12.810851Z"}, {"name": "execute", "started_at": "2023-12-27T16:38:12.823753Z", "completed_at": "2023-12-27T16:38:12.823760Z"}], "thread_id": "Thread-3 (worker)", "execution_time": 0.02359294891357422, "adapter_response": {}, "message": null, "failures": null, "unique_id": "model.zendesk.zendesk__ticket_enriched"}, {"status": "success", "timing": [{"name": "compile", "started_at": "2023-12-27T16:38:12.812336Z", "completed_at": "2023-12-27T16:38:12.825917Z"}, {"name": "execute", "started_at": "2023-12-27T16:38:12.840284Z", "completed_at": "2023-12-27T16:38:12.840291Z"}], "thread_id": "Thread-1 (worker)", "execution_time": 0.036054134368896484, "adapter_response": {}, "message": null, "failures": null, "unique_id": "model.zendesk.int_zendesk__comment_metrics"}, {"status": "success", "timing": [{"name": "compile", "started_at": "2023-12-27T16:38:12.849988Z", "completed_at": "2023-12-27T16:38:12.856979Z"}, {"name": "execute", "started_at": "2023-12-27T16:38:12.863141Z", "completed_at": "2023-12-27T16:38:12.863147Z"}], "thread_id": "Thread-1 (worker)", "execution_time": 0.016136884689331055, "adapter_response": {}, "message": null, "failures": null, "unique_id": "test.zendesk.not_null_zendesk__ticket_enriched_ticket_id.e3efc5bf0a"}, {"status": "success", "timing": [{"name": "compile", "started_at": "2023-12-27T16:38:12.853944Z", "completed_at": "2023-12-27T16:38:12.862866Z"}, {"name": "execute", "started_at": "2023-12-27T16:38:12.864526Z", "completed_at": "2023-12-27T16:38:12.864530Z"}], "thread_id": "Thread-2 (worker)", "execution_time": 0.01607799530029297, "adapter_response": {}, "message": null, "failures": null, "unique_id": "test.zendesk.unique_zendesk__ticket_enriched_ticket_id.7c3c6ca9ef"}, {"status": "success", "timing": [{"name": "compile", "started_at": "2023-12-27T16:38:12.532152Z", "completed_at": "2023-12-27T16:38:12.910306Z"}, {"name": "execute", "started_at": "2023-12-27T16:38:12.910847Z", "completed_at": "2023-12-27T16:38:12.910856Z"}], "thread_id": "Thread-4 (worker)", "execution_time": 0.38028597831726074, "adapter_response": {}, "message": null, "failures": null, "unique_id": "model.zendesk.int_zendesk__ticket_schedules"}, {"status": "success", "timing": [{"name": "compile", "started_at": "2023-12-27T16:38:12.914799Z", "completed_at": "2023-12-27T16:38:12.948389Z"}, {"name": "execute", "started_at": "2023-12-27T16:38:12.950219Z", "completed_at": "2023-12-27T16:38:12.950223Z"}], "thread_id": "Thread-3 (worker)", "execution_time": 0.03838515281677246, "adapter_response": {}, "message": null, "failures": null, "unique_id": "model.zendesk.int_zendesk__reply_time_business_hours"}, {"status": "success", "timing": [{"name": "compile", "started_at": "2023-12-27T16:38:12.938344Z", "completed_at": "2023-12-27T16:38:12.948660Z"}, {"name": "execute", "started_at": "2023-12-27T16:38:12.950493Z", "completed_at": "2023-12-27T16:38:12.950496Z"}], "thread_id": "Thread-4 (worker)", "execution_time": 0.038085222244262695, "adapter_response": {}, "message": null, "failures": null, "unique_id": "model.zendesk.int_zendesk__agent_work_time_business_hours"}, {"status": "success", "timing": [{"name": "compile", "started_at": "2023-12-27T16:38:12.953020Z", "completed_at": "2023-12-27T16:38:12.970114Z"}, {"name": "execute", "started_at": "2023-12-27T16:38:13.042797Z", "completed_at": "2023-12-27T16:38:13.042812Z"}], "thread_id": "Thread-2 (worker)", "execution_time": 0.11531615257263184, "adapter_response": {}, "message": null, "failures": null, "unique_id": "model.zendesk.int_zendesk__requester_wait_time_business_hours"}, {"status": "success", "timing": [{"name": "compile", "started_at": "2023-12-27T16:38:13.121235Z", "completed_at": "2023-12-27T16:38:13.137066Z"}, {"name": "execute", "started_at": "2023-12-27T16:38:13.150004Z", "completed_at": "2023-12-27T16:38:13.150013Z"}], "thread_id": "Thread-4 (worker)", "execution_time": 0.04881691932678223, "adapter_response": {}, "message": null, "failures": null, "unique_id": "model.zendesk.int_zendesk__reply_time_combined"}, {"status": "success", "timing": [{"name": "compile", "started_at": "2023-12-27T16:38:13.130751Z", "completed_at": "2023-12-27T16:38:13.189134Z"}, {"name": "execute", "started_at": "2023-12-27T16:38:13.197852Z", "completed_at": "2023-12-27T16:38:13.197860Z"}], "thread_id": "Thread-3 (worker)", "execution_time": 0.06835103034973145, "adapter_response": {}, "message": null, "failures": null, "unique_id": "model.zendesk.zendesk__ticket_metrics"}, {"status": "success", "timing": [{"name": "compile", "started_at": "2023-12-27T16:38:13.189606Z", "completed_at": "2023-12-27T16:38:13.199113Z"}, {"name": "execute", "started_at": "2023-12-27T16:38:13.201768Z", "completed_at": "2023-12-27T16:38:13.201775Z"}], "thread_id": "Thread-2 (worker)", "execution_time": 0.014636993408203125, "adapter_response": {}, "message": null, "failures": null, "unique_id": "model.zendesk.zendesk__sla_policies"}, {"status": "success", "timing": [{"name": "compile", "started_at": "2023-12-27T16:38:13.203452Z", "completed_at": "2023-12-27T16:38:13.211358Z"}, {"name": "execute", "started_at": "2023-12-27T16:38:13.216996Z", "completed_at": "2023-12-27T16:38:13.217003Z"}], "thread_id": "Thread-4 (worker)", "execution_time": 0.01729106903076172, "adapter_response": {}, "message": null, "failures": null, "unique_id": "model.zendesk.zendesk__ticket_summary"}, {"status": "success", "timing": [{"name": "compile", "started_at": "2023-12-27T16:38:13.206971Z", "completed_at": "2023-12-27T16:38:13.211669Z"}, {"name": "execute", "started_at": "2023-12-27T16:38:13.217362Z", "completed_at": "2023-12-27T16:38:13.217365Z"}], "thread_id": "Thread-3 (worker)", "execution_time": 0.017581939697265625, "adapter_response": {}, "message": null, "failures": null, "unique_id": "test.zendesk.not_null_zendesk__ticket_metrics_ticket_id.3466b76bbd"}, {"status": "success", "timing": [{"name": "compile", "started_at": "2023-12-27T16:38:13.211942Z", "completed_at": "2023-12-27T16:38:13.218229Z"}, {"name": "execute", "started_at": "2023-12-27T16:38:13.219995Z", "completed_at": "2023-12-27T16:38:13.219999Z"}], "thread_id": "Thread-2 (worker)", "execution_time": 0.010115861892700195, "adapter_response": {}, "message": null, "failures": null, "unique_id": "test.zendesk.unique_zendesk__ticket_metrics_ticket_id.f3dc8eba5c"}, {"status": "success", "timing": [{"name": "compile", "started_at": "2023-12-27T16:38:13.221012Z", "completed_at": "2023-12-27T16:38:13.224345Z"}, {"name": "execute", "started_at": "2023-12-27T16:38:13.225026Z", "completed_at": "2023-12-27T16:38:13.225036Z"}], "thread_id": "Thread-4 (worker)", "execution_time": 0.006000041961669922, "adapter_response": {}, "message": null, "failures": null, "unique_id": "test.zendesk.unique_zendesk__sla_policies_sla_event_id.5daff4d2bd"}, {"status": "success", "timing": [{"name": "compile", "started_at": "2023-12-27T16:38:12.866852Z", "completed_at": "2023-12-27T16:38:13.257189Z"}, {"name": "execute", "started_at": "2023-12-27T16:38:13.259552Z", "completed_at": "2023-12-27T16:38:13.259562Z"}], "thread_id": "Thread-1 (worker)", "execution_time": 0.3955719470977783, "adapter_response": {}, "message": null, "failures": null, "unique_id": "model.zendesk.int_zendesk__field_history_pivot"}, {"status": "success", "timing": [{"name": "compile", "started_at": "2023-12-27T16:38:13.263350Z", "completed_at": "2023-12-27T16:38:13.712404Z"}, {"name": "execute", "started_at": "2023-12-27T16:38:13.713769Z", "completed_at": "2023-12-27T16:38:13.713787Z"}], "thread_id": "Thread-3 (worker)", "execution_time": 0.5045931339263916, "adapter_response": {}, "message": null, "failures": null, "unique_id": "model.zendesk.int_zendesk__field_history_scd"}, {"status": "success", "timing": [{"name": "compile", "started_at": "2023-12-27T16:38:13.769242Z", "completed_at": "2023-12-27T16:38:14.208215Z"}, {"name": "execute", "started_at": "2023-12-27T16:38:14.208748Z", "completed_at": "2023-12-27T16:38:14.208756Z"}], "thread_id": "Thread-4 (worker)", "execution_time": 0.4995110034942627, "adapter_response": {}, "message": null, "failures": null, "unique_id": "model.zendesk.zendesk__ticket_field_history"}, {"status": "success", "timing": [{"name": "compile", "started_at": "2023-12-27T16:38:14.270214Z", "completed_at": "2023-12-27T16:38:14.279704Z"}, {"name": "execute", "started_at": "2023-12-27T16:38:14.280241Z", "completed_at": "2023-12-27T16:38:14.280248Z"}], "thread_id": "Thread-2 (worker)", "execution_time": 0.011296987533569336, "adapter_response": {}, "message": null, "failures": null, "unique_id": "model.zendesk.zendesk__ticket_backlog"}], "elapsed_time": 7.817997217178345, "args": {"version_check": true, "write_json": true, "exclude": [], "profiles_dir": "/Users/joseph.markiewicz/.dbt", "log_format": "default", "enable_legacy_logger": false, "cache_selected_only": false, "indirect_selection": "eager", "log_format_file": "debug", "log_file_max_bytes": 10485760, "favor_state": false, "populate_cache": true, "invocation_command": "dbt docs generate -t postgres", "macro_debugging": false, "static_parser": true, "target": "postgres", "use_colors": true, "empty_catalog": false, "log_path": "/Users/joseph.markiewicz/Documents/dbt_packages/zendesk/dbt_zendesk/integration_tests/logs", "vars": {}, "log_level": "info", "print": true, "compile": true, "send_anonymous_usage_stats": true, "use_colors_file": true, "warn_error_options": {"include": [], "exclude": []}, "defer": false, "log_level_file": "debug", "printer_width": 80, "which": "generate", "partial_parse": true, "partial_parse_file_diff": true, "project_dir": "/Users/joseph.markiewicz/Documents/dbt_packages/zendesk/dbt_zendesk/integration_tests", "strict_mode": false, "introspect": true, "quiet": false, "select": []}}